<?xml version="1.0" encoding="UTF-8"?>

<!-- generated on 08/13/20 13:01:09 by Eclipse SUMO GUI Version 1.6.0
<configuration xmlns:xsi="http://www.w3.org/2001/XMLSchema-instance" xsi:noNamespaceSchemaLocation="http://sumo.dlr.de/xsd/sumoConfiguration.xsd">

    <input>
        <net-file value="C:\Users\REVSMILE\Documents\Sumo\Demo3\4way\4way.net.xml"/>
        <route-files value="C:\Users\REVSMILE\Documents\Sumo\Demo3\4way\4way.rou.xml"/>
        <additional-files value="C:\Users\REVSMILE\Documents\Sumo\Demo3\4way\4way.add.xml"/>
    </input>

</configuration>
-->

<detector xmlns:xsi="http://www.w3.org/2001/XMLSchema-instance" xsi:noNamespaceSchemaLocation="http://sumo.dlr.de/xsd/det_e1_file.xsd">
    <interval begin="0.00" end="439.00" id="det_0" nVehContrib="18" flow="147.61" occupancy="33.69" speed="5.37" harmonicMeanSpeed="0.61" length="5.33" nVehEntered="18"/>
    <interval begin="0.00" end="439.00" id="det_1" nVehContrib="33" flow="270.62" occupancy="69.70" speed="3.20" harmonicMeanSpeed="0.54" length="5.18" nVehEntered="33"/>
    <interval begin="0.00" end="439.00" id="det_2" nVehContrib="22" flow="180.41" occupancy="59.17" speed="4.10" harmonicMeanSpeed="0.57" length="5.64" nVehEntered="22"/>
    <interval begin="0.00" end="439.00" id="det_3" nVehContrib="22" flow="180.41" occupancy="18.03" speed="3.94" harmonicMeanSpeed="1.71" length="5.64" nVehEntered="22"/>
</detector>
